hivemind_audio_binary_protocol/__init__.py
hivemind_audio_binary_protocol/protocol.py
hivemind_audio_binary_protocol/transformers.py
hivemind_audio_binary_protocol/version.py
hivemind_audio_binary_protocol-2.1.3.dist-info/licenses/LICENSE
hivemind_audio_binary_protocol-2.1.3.dist-info/METADATA
hivemind_audio_binary_protocol-2.1.3.dist-info/WHEEL
hivemind_audio_binary_protocol-2.1.3.dist-info/entry_points.txt
hivemind_audio_binary_protocol-2.1.3.dist-info/top_level.txt
hivemind_audio_binary_protocol-2.1.3.dist-info/RECORD
