Metadata-Version: 2.4
Name: hivemind-audio-binary-protocol
Version: 2.1.3
Summary: Mesh Networking utilities for OpenVoiceOS
Home-page: https://github.com/JarbasHiveMind/hivemind-audio-binary-protocol
Author: jarbasAI
Author-email: jarbasai@mailfence.com
License: Apache2.0
License-File: LICENSE
Requires-Dist: ovos-simple-listener
Requires-Dist: hivemind_bus_client<1.0.0,>=0.1.0
Requires-Dist: ovos-plugin-manager<3.0.0
Requires-Dist: hivemind-core<4.0.0,>=1.0.0
Requires-Dist: click
Dynamic: author
Dynamic: author-email
Dynamic: home-page
Dynamic: license
Dynamic: license-file
Dynamic: requires-dist
Dynamic: summary
